convection/secrets/client/__init__.py
convection/secrets/client/console.py
convection/secrets/client/api/acl.py
convection/secrets/client/api/auth.py
convection/secrets/client/api/core.py
convection/secrets/client/api/group.py
convection/secrets/client/api/keys.py
convection/secrets/client/api/secrets.py
convection/secrets/client/api/store.py
convection/secrets/client/api/user.py
convection/secrets/client/specs/secrets-console.global.secrets.client.spec
convection/secrets/client/specs/secrets-console.global.secrets.spec
convection/secrets/client/specs/secrets-console.global.spec
convection/secrets/client/specs/secrets-console.spec
convection_secrets_client-1.1.0.dist-info/LICENSE.md
convection_secrets_client-1.1.0.dist-info/METADATA
convection_secrets_client-1.1.0.dist-info/WHEEL
convection_secrets_client-1.1.0.dist-info/entry_points.txt
convection_secrets_client-1.1.0.dist-info/top_level.txt
convection_secrets_client-1.1.0.dist-info/RECORD
