Metadata-Version: 2.1
Name: convection-secrets-client
Version: 1.1.0
Summary: Convection Secrets Client
Author-email: AccidentallyTheCable <cableninja@cableninja.net>
License: GPLv3
Project-URL: Homepage, https://gitlab.com/accidentallythecable-public/convection-suite/convection-secrets-client/
Project-URL: Bug Tracker, https://gitlab.com/accidentallythecable-public/convection-suite/convection-secrets-client/issues
Classifier: Programming Language :: Python :: 3
Classifier: License :: OSI Approved :: GNU General Public License v3 (GPLv3)
Classifier: Operating System :: OS Independent
Classifier: Topic :: Security
Classifier: Topic :: Security :: Cryptography
Requires-Python: >=3.9
License-File: LICENSE.md
Requires-Dist: argstruct <2.0,>=1.0
Requires-Dist: tabulate <1.0
Requires-Dist: cryptography >=41.0
Requires-Dist: types-cryptography <4.0,>=3.3
Requires-Dist: types-tabulate <1.0
Requires-Dist: atckit <2.0,>=1.0
Requires-Dist: convection-shared <2.0,>=1.0
